napari_easy_augment_batch_dl/__init__.py
napari_easy_augment_batch_dl/bounding_box_util.py
napari_easy_augment_batch_dl/deep_learning_project.py
napari_easy_augment_batch_dl/deep_learning_widget.py
napari_easy_augment_batch_dl/easy_augment_batch_dl.py
napari_easy_augment_batch_dl/interactive_launch.py
napari_easy_augment_batch_dl/napari.yaml
napari_easy_augment_batch_dl/utility.py
napari_easy_augment_batch_dl/widgets.py
napari_easy_augment_batch_dl/zarr_helper.py
napari_easy_augment_batch_dl/_tests/__init__.py
napari_easy_augment_batch_dl/_tests/test_deep_learning_project.py
napari_easy_augment_batch_dl/frameworks/base_framework.py
napari_easy_augment_batch_dl/frameworks/cellpose_instance_framework.py
napari_easy_augment_batch_dl/frameworks/mobile_sam_framework.py
napari_easy_augment_batch_dl/frameworks/pytorch_semantic_dataset.py
napari_easy_augment_batch_dl/frameworks/pytorch_semantic_framework.py
napari_easy_augment_batch_dl/frameworks/random_forest_framework.py
napari_easy_augment_batch_dl/frameworks/stardist_instance_framework.py
napari_easy_augment_batch_dl/frameworks/training_features.py
napari_easy_augment_batch_dl/frameworks/yolo_sam_framework.py
napari_easy_augment_batch_dl-0.0.6.dist-info/licenses/LICENSE
napari_easy_augment_batch_dl-0.0.6.dist-info/METADATA
napari_easy_augment_batch_dl-0.0.6.dist-info/WHEEL
napari_easy_augment_batch_dl-0.0.6.dist-info/entry_points.txt
napari_easy_augment_batch_dl-0.0.6.dist-info/top_level.txt
napari_easy_augment_batch_dl-0.0.6.dist-info/RECORD
