Metadata-Version: 2.4
Name: napari-easy-augment-batch-dl
Version: 0.0.6
Summary: A plugin to perform unet based deep learning with a small number of labels and augmentation
Author: Brian Northan
Author-email: bnorthan@gmail.com
License: 
Project-URL: Bug Tracker, https://github.com/bnorthan/napari-easy-augment-batch-dl/issues
Project-URL: Documentation, https://github.com/bnorthan/napari-easy-augment-batch-dl#README.md
Project-URL: Source Code, https://github.com/bnorthan/napari-easy-augment-batch-dl
Project-URL: User Support, https://github.com/bnorthan/napari-easy-augment-batch-dl/issues
Classifier: Development Status :: 2 - Pre-Alpha
Classifier: Framework :: napari
Classifier: Intended Audience :: Developers
Classifier: License :: OSI Approved :: BSD License
Classifier: Operating System :: OS Independent
Classifier: Programming Language :: Python
Classifier: Programming Language :: Python :: 3
Classifier: Programming Language :: Python :: 3 :: Only
Classifier: Programming Language :: Python :: 3.9
Classifier: Programming Language :: Python :: 3.10
Classifier: Programming Language :: Python :: 3.11
Classifier: Programming Language :: Python :: 3.12
Classifier: Topic :: Scientific/Engineering :: Image Processing
Requires-Python: >=3.9
License-File: LICENSE
Requires-Dist: numpy
Requires-Dist: magicgui
Requires-Dist: qtpy
Requires-Dist: scikit-image
Requires-Dist: tnia-python
Provides-Extra: testing
Requires-Dist: tox; extra == "testing"
Requires-Dist: pytest; extra == "testing"
Requires-Dist: pytest-cov; extra == "testing"
Requires-Dist: pytest-qt; extra == "testing"
Requires-Dist: napari; extra == "testing"
Requires-Dist: pyqt5; extra == "testing"
Dynamic: license-file
